bark/__init__.py
bark/api.py
bark/generation.py
bark/model.py
bark/model_fine.py
bark/assets/prompts/announcer.npz
bark/assets/prompts/de_speaker_0.npz
bark/assets/prompts/de_speaker_1.npz
bark/assets/prompts/de_speaker_2.npz
bark/assets/prompts/de_speaker_3.npz
bark/assets/prompts/de_speaker_4.npz
bark/assets/prompts/de_speaker_5.npz
bark/assets/prompts/de_speaker_6.npz
bark/assets/prompts/de_speaker_7.npz
bark/assets/prompts/de_speaker_8.npz
bark/assets/prompts/de_speaker_9.npz
bark/assets/prompts/en_speaker_0.npz
bark/assets/prompts/en_speaker_1.npz
bark/assets/prompts/en_speaker_2.npz
bark/assets/prompts/en_speaker_3.npz
bark/assets/prompts/en_speaker_4.npz
bark/assets/prompts/en_speaker_5.npz
bark/assets/prompts/en_speaker_6.npz
bark/assets/prompts/en_speaker_7.npz
bark/assets/prompts/en_speaker_8.npz
bark/assets/prompts/en_speaker_9.npz
bark/assets/prompts/es_speaker_0.npz
bark/assets/prompts/es_speaker_1.npz
bark/assets/prompts/es_speaker_2.npz
bark/assets/prompts/es_speaker_3.npz
bark/assets/prompts/es_speaker_4.npz
bark/assets/prompts/es_speaker_5.npz
bark/assets/prompts/es_speaker_6.npz
bark/assets/prompts/es_speaker_7.npz
bark/assets/prompts/es_speaker_8.npz
bark/assets/prompts/es_speaker_9.npz
bark/assets/prompts/fr_speaker_0.npz
bark/assets/prompts/fr_speaker_1.npz
bark/assets/prompts/fr_speaker_2.npz
bark/assets/prompts/fr_speaker_3.npz
bark/assets/prompts/fr_speaker_4.npz
bark/assets/prompts/fr_speaker_5.npz
bark/assets/prompts/fr_speaker_6.npz
bark/assets/prompts/fr_speaker_7.npz
bark/assets/prompts/fr_speaker_8.npz
bark/assets/prompts/fr_speaker_9.npz
bark/assets/prompts/hi_speaker_0.npz
bark/assets/prompts/hi_speaker_1.npz
bark/assets/prompts/hi_speaker_2.npz
bark/assets/prompts/hi_speaker_3.npz
bark/assets/prompts/hi_speaker_4.npz
bark/assets/prompts/hi_speaker_5.npz
bark/assets/prompts/hi_speaker_6.npz
bark/assets/prompts/hi_speaker_7.npz
bark/assets/prompts/hi_speaker_8.npz
bark/assets/prompts/hi_speaker_9.npz
bark-0.1.5.dist-info/LICENSE
bark-0.1.5.dist-info/METADATA
bark-0.1.5.dist-info/WHEEL
bark-0.1.5.dist-info/top_level.txt
bark-0.1.5.dist-info/RECORD
